src/__init__.py
src/gtr.py
github_trending_repos-1.1.4.dist-info/LICENSE
github_trending_repos-1.1.4.dist-info/METADATA
github_trending_repos-1.1.4.dist-info/WHEEL
github_trending_repos-1.1.4.dist-info/entry_points.txt
github_trending_repos-1.1.4.dist-info/top_level.txt
github_trending_repos-1.1.4.dist-info/RECORD
