Metadata-Version: 2.1
Name: github-trending-repos
Version: 1.1.4
Summary: A CLI tool for retrieving trending GitHub repositories.
License-File: LICENSE
Requires-Dist: beautifulsoup4 (==4.12.2)
Requires-Dist: PyTermGUI (==7.7.0)
Requires-Dist: requests (==2.31.0)
